widlparser/__init__.py
widlparser/constructs.py
widlparser/markup.py
widlparser/parser.py
widlparser/productions.py
widlparser/protocols.py
widlparser/py.typed
widlparser/tokenizer.py
widlparser-1.3.1.dist-info/METADATA
widlparser-1.3.1.dist-info/WHEEL
widlparser-1.3.1.dist-info/top_level.txt
widlparser-1.3.1.dist-info/RECORD
