Metadata-Version: 2.4
Name: widlparser
Version: 1.3.1
Summary: WebIDL Parser
Author-email: Peter Linss <pypi@linss.com>
License: MIT Licence
Project-URL: homepage, https://gitlab.linss.com/open-source/python/widlparser
Keywords: config
Classifier: Intended Audience :: Developers
Classifier: License :: OSI Approved :: MIT License
Classifier: Programming Language :: Python
Classifier: Programming Language :: Python :: 3
Classifier: Programming Language :: Python :: 3.9
Classifier: Programming Language :: Python :: 3.10
Classifier: Programming Language :: Python :: 3.11
Classifier: Programming Language :: Python :: 3.12
Classifier: Programming Language :: Python :: 3.13
Classifier: Topic :: Software Development :: Libraries :: Python Modules
Requires-Python: >=3.9
Provides-Extra: dev
Requires-Dist: types-PyYAML; extra == "dev"
Requires-Dist: mypy; extra == "dev"
Requires-Dist: flake8; extra == "dev"
Requires-Dist: flake8-annotations; extra == "dev"
Requires-Dist: flake8-bandit; extra == "dev"
Requires-Dist: flake8-bugbear; extra == "dev"
Requires-Dist: flake8-commas; extra == "dev"
Requires-Dist: flake8-comprehensions; extra == "dev"
Requires-Dist: flake8-continuation; extra == "dev"
Requires-Dist: flake8-datetimez; extra == "dev"
Requires-Dist: flake8-docstrings; extra == "dev"
Requires-Dist: flake8-import-order; extra == "dev"
Requires-Dist: flake8-literal; extra == "dev"
Requires-Dist: flake8-modern-annotations; extra == "dev"
Requires-Dist: flake8-noqa; extra == "dev"
Requires-Dist: flake8-pyproject; extra == "dev"
Requires-Dist: flake8-requirements; extra == "dev"
Requires-Dist: flake8-typechecking-import; extra == "dev"
Requires-Dist: flake8-use-fstring; extra == "dev"
Requires-Dist: pep8-naming; extra == "dev"
